apifiny_futures/__init__.py
apifiny_futures/__version__.py
apifiny_futures/fut_websocket.py
apifiny_futures/rest_api.py
apifiny_futures/rest_market.py
apifiny_futures/lib/__init__.py
apifiny_futures/lib/apifiny_urls.py
apifiny_futures/lib/utils.py
apifiny_futures/lib/venue_list.py
apifiny_futures-1.0.0.dist-info/LICENSE
apifiny_futures-1.0.0.dist-info/METADATA
apifiny_futures-1.0.0.dist-info/WHEEL
apifiny_futures-1.0.0.dist-info/top_level.txt
apifiny_futures-1.0.0.dist-info/RECORD
