Metadata-Version: 2.1
Name: apifiny-futures
Version: 1.0.0
Summary: This is a library that works as a connector to Apifiny Futures OPEN API.
Home-page: https://github.com/Apifiny-IO/apifiny-futures-connector-python
Author: Apifiny
Maintainer: Liuke
License: MIT
Keywords: apifiny,api,unified APIs,connect,market data,cryptocurrency,tickdata,spot,futures,orderbook data,executed transactions data,history market data,real time market data,fix protocol,websocket api,http api,rest api,fix api
Classifier: Development Status :: 5 - Production/Stable
Classifier: Intended Audience :: Developers
Classifier: Intended Audience :: Financial and Insurance Industry
Classifier: Intended Audience :: End Users/Desktop
Classifier: License :: OSI Approved :: MIT License
Classifier: Programming Language :: Python :: 3.7
Classifier: Programming Language :: Python :: 3.8
Classifier: Programming Language :: Python :: 3.9
Classifier: Programming Language :: Python :: 3.10
Requires-Python: >=3.7
License-File: LICENSE
Requires-Dist: requests (==2.26.0)
Requires-Dist: websocket-client (==1.0.1)
